pyki3oom/__init__.py
pyki3oom/ki3oom.py
pyki3oom/parser.py
pyki3oom-0.0.4.dist-info/LICENSE
pyki3oom-0.0.4.dist-info/METADATA
pyki3oom-0.0.4.dist-info/WHEEL
pyki3oom-0.0.4.dist-info/top_level.txt
pyki3oom-0.0.4.dist-info/RECORD
