Metadata-Version: 2.1
Name: pyki3oom
Version: 0.0.4
Summary: python wrapper for Kiwoom Open API+ (Korea Stock Market)
Home-page: UNKNOWN
Author: ador hylas
Author-email: null@gmail.com
License: MIT
Platform: UNKNOWN
Requires-Dist: PyQt5 (==5.15.2)
Requires-Dist: pandas (==1.2.1)
